pbincli/__init__.py
pbincli/actions.py
pbincli/api.py
pbincli/cli.py
pbincli/format.py
pbincli/utils.py
pbincli-0.3.7.dist-info/licenses/LICENSE
pbincli-0.3.7.dist-info/METADATA
pbincli-0.3.7.dist-info/WHEEL
pbincli-0.3.7.dist-info/entry_points.txt
pbincli-0.3.7.dist-info/top_level.txt
pbincli-0.3.7.dist-info/RECORD
