Metadata-Version: 2.4
Name: PBinCLI
Version: 0.3.7
Summary: PrivateBin client for command line
Home-page: https://github.com/r4sas/PBinCLI/
Author: R4SAS
Author-email: r4sas@i2pmail.org
License: MIT
Project-URL: Bug Reports, https://github.com/r4sas/PBinCLI/issues
Project-URL: Source, https://github.com/r4sas/PBinCLI/
Keywords: privatebin cryptography security
Classifier: Development Status :: 5 - Production/Stable
Classifier: Environment :: Console
Classifier: Intended Audience :: End Users/Desktop
Classifier: License :: OSI Approved :: MIT License
Classifier: Programming Language :: Python :: 3
Classifier: Topic :: Security :: Cryptography
Classifier: Topic :: Utilities
Requires-Python: >=3
License-File: LICENSE
Requires-Dist: pycryptodome
Requires-Dist: sjcl
Requires-Dist: base58
Requires-Dist: requests
Requires-Dist: argcomplete
Requires-Dist: pysocks
Dynamic: author
Dynamic: author-email
Dynamic: classifier
Dynamic: description
Dynamic: description-content-type
Dynamic: home-page
Dynamic: keywords
Dynamic: license
Dynamic: license-file
Dynamic: project-url
Dynamic: requires-dist
Dynamic: requires-python
Dynamic: summary
